{"_id": "6a1ea29cc06aac41db3a888d", "id": "Shivam4096/Carpool", "sdk": "docker", "likes": 0, "tags": ["docker", "region:us"], "private": false, "author": "Shivam4096", "sha": "0541004f15bede85207c5494b10557f8388c607d", "lastModified": "2026-06-02T10:04:04.000Z", "cardData": {"title": "Carpool", "emoji": "\ud83d\ude97", "colorFrom": "blue", "colorTo": "green", "sdk": "docker", "pinned": false}, "subdomain": "shivam4096-carpool", "gated": false, "disabled": false, "host": "https://shivam4096-carpool.hf.space", "runtime": {"stage": "RUNTIME_ERROR", "hardware": {"current": null, "requested": "cpu-basic"}, "gcTimeout": 172800, "errorMessage": "Exit code: 1. Reason: \u25c7 injected env (8) from .env // tip: \u2318 multiple files { path: ['.env.local', '.env'] }\n[AI] \u2705 NVIDIA NIM ready \u2014 model: meta/llama-3.3-70b-instruct\n[AI] Active provider: NVIDIA\n/app/server/node_modules/path-to-regexp/dist/index.js:108\n                    throw new PathError(`Missing parameter name at index ${index}`, str);\n                    ^\n\nPathError [TypeError]: Missing parameter name at index 1: *; visit https://git.new/pathToRegexpError for info\n    at consumeUntil (/app/server/node_modules/path-to-regexp/dist/index.js:108:27)\n    at parse (/app/server/node_modules/path-to-regexp/dist/index.js:140:26)\n    at process (/app/server/node_modules/path-to-regexp/dist/index.js:263:56)\n    at pathToRegexp (/app/server/node_modules/path-to-regexp/dist/index.js:274:5)\n    at Object.match (/app/server/node_modules/path-to-regexp/dist/index.js:225:30)\n    at matcher (/app/server/node_modules/router/lib/layer.js:86:23)\n    at new Layer (/app/server/node_modules/router/lib/layer.js:93:62)\n    at Function.route (/app/server/node_modules/router/index.js:428:17)\n    at Function.route (/app/server/node_modules/express/lib/application.js:257:22)\n    at app.<computed> [as get] (/app/server/node_modules/express/lib/application.js:478:22) {\n  originalPath: '*'\n}\n\nNode.js v20.20.2\n", "replicas": {"requested": 1}, "devMode": false, "domains": [{"domain": "shivam4096-carpool.hf.space", "stage": "READY"}]}, "siblings": [{"rfilename": ".dockerignore"}, {"rfilename": ".gitignore"}, {"rfilename": "Carpool_Implementation_Plan.docx"}, {"rfilename": "Dockerfile"}, {"rfilename": "README.md"}, {"rfilename": "Reliance_Carpool_Full_Documentation.docx"}, {"rfilename": "Reliance_Carpool_Product_Document.docx"}, {"rfilename": "ai_studio_export.md"}, {"rfilename": "eslint.config.js"}, {"rfilename": "extract_doc.py"}, {"rfilename": "generate_doc.cjs"}, {"rfilename": "generate_full_doc.cjs"}, {"rfilename": "index.html"}, {"rfilename": "package-lock.json"}, {"rfilename": "package.json"}, {"rfilename": "postcss.config.js"}, {"rfilename": "public/favicon.svg"}, {"rfilename": "public/icons.svg"}, {"rfilename": "public/sw.js"}, {"rfilename": "replace.cjs"}, {"rfilename": "replace_urls.cjs"}, {"rfilename": "server/.env"}, {"rfilename": "server/check.js"}, {"rfilename": "server/check_all.js"}, {"rfilename": "server/database.sqlite"}, {"rfilename": "server/insert_admin.js"}, {"rfilename": "server/migrate_poolhost.js"}, {"rfilename": "server/migrate_users.js"}, {"rfilename": "server/package-lock.json"}, {"rfilename": "server/package.json"}, {"rfilename": "server/server.js"}, {"rfilename": "server/test_nvidia.js"}, {"rfilename": "src/AIChat.jsx"}, {"rfilename": "src/App.css"}, {"rfilename": "src/App.jsx"}, {"rfilename": "src/AppLayout.jsx"}, {"rfilename": "src/ChatModal.jsx"}, {"rfilename": "src/ESGDashboard.jsx"}, {"rfilename": "src/IncidentQueue.jsx"}, {"rfilename": "src/MapComponent.jsx"}, {"rfilename": "src/PassengerDashboard.jsx"}, {"rfilename": "src/PoolHostDashboard.jsx"}, {"rfilename": "src/Registration.jsx"}, {"rfilename": "src/Settings.jsx"}, {"rfilename": "src/SwipeToComplete.jsx"}, {"rfilename": "src/TripsDashboard.jsx"}, {"rfilename": "src/UserManagement.jsx"}, {"rfilename": "src/UserPortal.jsx"}, {"rfilename": "src/VerificationQueue.jsx"}, {"rfilename": "src/assets/hero.png"}, {"rfilename": "src/assets/react.svg"}, {"rfilename": "src/assets/vite.svg"}, {"rfilename": "src/index.css"}, {"rfilename": "src/main.jsx"}, {"rfilename": "src/pushUtils.js"}, {"rfilename": "tailwind.config.js"}, {"rfilename": "test.js"}, {"rfilename": "tester-agent.cjs"}, {"rfilename": "update_doc.py"}, {"rfilename": "update_doc2.py"}, {"rfilename": "vite.config.js"}, {"rfilename": "~$liance_Carpool_Full_Documentation.docx"}], "createdAt": "2026-06-02T09:30:04.000Z", "usedStorage": 0}